browser_transcribe/__init__.py
browser_transcribe/example.py
browser_transcribe/frontend/index.html
streamlit_browser_transcribe-0.0.1.dist-info/LICENSE
streamlit_browser_transcribe-0.0.1.dist-info/METADATA
streamlit_browser_transcribe-0.0.1.dist-info/WHEEL
streamlit_browser_transcribe-0.0.1.dist-info/top_level.txt
streamlit_browser_transcribe-0.0.1.dist-info/RECORD
